<?xml version="1.0" encoding="UTF-8"?><record_update table="sp_container">
    <sp_container action="INSERT_OR_UPDATE">
        <background_color/>
        <background_image/>
        <background_style>default</background_style>
        <bootstrap_alt>false</bootstrap_alt>
        <class_name>homepage-quicklinks</class_name>
        <container_class_name/>
        <name>AE IT ITSM Page - Container 4</name>
        <order>4</order>
        <sp_page display_value="ae_it_ctsm_services_itsm_landing">8216c0e6db62b34018159c29db9619f3</sp_page>
        <subheader>false</subheader>
        <sys_class_name>sp_container</sys_class_name>
        <sys_created_by>williamsbr.local</sys_created_by>
        <sys_created_on>2019-07-15 20:02:06</sys_created_on>
        <sys_customer_update>false</sys_customer_update>
        <sys_id>2fa69ca3dba2f3404a1192a6db9619bb</sys_id>
        <sys_mod_count>3</sys_mod_count>
        <sys_name>AE IT ITSM Page - Container 4</sys_name>
        <sys_package display_value="AE IT Service Portal" source="x_aue_ae_it_servic">d7c8b857db16f30018159c29db96193d</sys_package>
        <sys_policy/>
        <sys_replace_on_upgrade>false</sys_replace_on_upgrade>
        <sys_scope display_value="AE IT Service Portal">d7c8b857db16f30018159c29db96193d</sys_scope>
        <sys_update_name>sp_container_2fa69ca3dba2f3404a1192a6db9619bb</sys_update_name>
        <sys_updated_by>williamsbr.local</sys_updated_by>
        <sys_updated_on>2019-07-15 20:06:59</sys_updated_on>
        <title>Quick Links</title>
        <width>container</width>
    </sp_container>
</record_update>
